setup.cfg
setup.py
logging_rollbar/__init__.py
logging_rollbar/config.py
logging_rollbar/handlers.py
logging_rollbar.egg-info/PKG-INFO
logging_rollbar.egg-info/SOURCES.txt
logging_rollbar.egg-info/dependency_links.txt
logging_rollbar.egg-info/requires.txt
logging_rollbar.egg-info/top_level.txt