Metadata-Version: 1.1
Name: logging-rollbar
Version: 0.2
Summary: An implementation of the python logging library with support for rollbar
Home-page: https://github.com/lucien2k/logging-rollbar
Author: Alex Cowan
Author-email: alex@razorsecure.com
License: MIT
Download-URL: https://github.com/lucien2k/logging_rollbar/archive/0.2.tar.gz
Keywords: logging,rollbar
Platform: UNKNOWN
